{"validation":{"listApplication":{"approveStatus":20,"badData":"Y","pushDown":"N","keyBasedRecordCountAnomaly":"N","dupRowIdentityThreshold":0,"recordAnomalyCheck":"Y","historicEndDate":null,"incrementalTimestamp":null,"applyDerivedColumns":"N","offsetValue":null,"historicStartDate":null,"data_domain":2,"thresholdsApplyOption":0,"trimFunctionforMatch":"N","continuousFileMonitoring":"N","outOfNormCheck":"N","numericalStatThreshold":null,"entityColumn":"N","active":"yes","rollType":null,"endDateChk":null,"priority":null,"frequencyday":"unknown","fileNameValidation":"N","stringStatThreshold":null,"stagingApproveStatus":16,"updateFrequency":"Never","schema":null,"approveDate":null,"keyGroupRecordCountAnomaly":"N","timelinessKeyChk":"N","startDateChk":null,"coalesceFunctionforMatch":"N","appType":"Data Forensics","startTime":null,"maxLengthCheck":"Y","stringStatCheck":"N","recordCountAnomalyThreshold":3,"correlationcheck":null,"lengthCheckThreshold":null,"workspaceId":null,"castFunctionforMatch":"N","dataDriftThreshold":null,"groupEquality":"N","sigmaCalcDays":0,"nonNullCheck":"Y","workspaceDomain":null,"idRightData":0,"frequencyDays":0,"automated":"N","dupRowAllThreshold":0,"endTime":null,"dataDriftCheck":"Y","recordCountAnomaly":"Y","fileMonitoringType":null,"dataTrustMetricsCheck":"N","criticalRuleAvailable":null,"enablePhoneticMatching":null,"dGroupDateRuleCheck":"N","approveBy":0,"validityThreshold":1,"frequency":"unknown","approverName":"Admin User","createdAt":null,"duplicateCheck":null,"garbageRows":0,"idLeftData":0,"defaultPatternCheck":"Y","buildHistoricFingerPrint":"N","updatedAt":null,"updatedBy":null,"idData":27461,"colOrderValidation":"N","rollTargetSchemaId":0,"domainId":129,"slatime":null,"applyRules":"N","domainName":"Rajtesting","reprofiling":"N","name":"31646_Query_condition_Validation","isSegment":"N","projectName":"Rut_Loan","projectId":148,"buildHistoricDayByDay":"N","tagIdList":null,"historicDateFormat":null,"subcribedEmailId":null,"patternCheck":"Y","createdByUser":null,"groupEqualityThreshold":0,"description":"A default validation check","dGroupNullCheck":"N","accuracyRate":0,"recordAnomalyThreshold":null,"timeSeries":"None","dupRowIdentity":"Y","nonNullThreshold":null,"dupRowAll":"Y","defaultValues":null,"windowTime":0,"csvDir":null,"prefix1":null,"dGroupDataDriftCheck":"N","numericalStatCheck":"Y","prefix2":null,"lengthCheck":"Y","matchingThreshold":0,"incrementalMatching":"N","defaultCheck":"Y","validationJobSize":"medium","approveComments":null,"workspaceSubdomain":null,"idApp":31646,"createdBy":null,"dateRuleChk":"Y"},"ruleCatalog":{"catalogRulesList":[{"ruleCategory":"Auto Discovery","ruleReference":44,"tagId":[],"rightTemplateFilterCondition":"","threshold":3,"ruleExpression":"2","dimensionName":"Completeness","ruleDescription":"Elements w/Invalid length < Threshold","rowId":1294528,"suggestionReason":"","idApp":31646,"ruleCode":"0","businessAttributes":"","defectCode":"","dimensionId":3,"ruleType":"Length Check","customOrGlobalRuleId":0,"agingCheckEnabled":"N","ruleName":"AutoDiscovery_LengthCheck_EMP_ID","nullFilterColumn":"EMP_ID","businessAttributeId":"","columnName":"EMP_ID","activeFlag":false},{"ruleCategory":"Auto Discovery","ruleReference":57,"tagId":[],"rightTemplateFilterCondition":"","threshold":3,"ruleExpression":"","dimensionName":"Consistency","ruleDescription":"Entire microsegment behavior deviates from history < Threshold","rowId":1294554,"suggestionReason":"","idApp":31646,"ruleCode":"0","businessAttributes":"","defectCode":"","dimensionId":4,"ruleType":"Numerical Statistics Check","customOrGlobalRuleId":0,"agingCheckEnabled":"N","ruleName":"AutoDiscovery_NumericalStatisticsCheck_AGE_EMP","nullFilterColumn":"AGE_EMP","businessAttributeId":"","columnName":"AGE_EMP","activeFlag":false},{"ruleCategory":"Auto Discovery","ruleReference":45,"tagId":[],"rightTemplateFilterCondition":"","threshold":3,"ruleExpression":"4","dimensionName":"Completeness","ruleDescription":"Elements w/Invalid length < Threshold","rowId":1294529,"suggestionReason":"","idApp":31646,"ruleCode":"0","businessAttributes":"","defectCode":"","dimensionId":3,"ruleType":"Length Check","customOrGlobalRuleId":0,"agingCheckEnabled":"N","ruleName":"AutoDiscovery_LengthCheck_CITY","nullFilterColumn":"CITY","businessAttributeId":"","columnName":"CITY","activeFlag":false},{"ruleCategory":"Auto Discovery","ruleReference":48,"tagId":[],"rightTemplateFilterCondition":"","threshold":3,"ruleExpression":"","dimensionName":"Validity","ruleDescription":"Invalid data type < Threshold","rowId":1294537,"suggestionReason":"","idApp":31646,"ruleCode":"0","businessAttributes":"","defectCode":"","dimensionId":2,"ruleType":"Bad Data Check","customOrGlobalRuleId":0,"agingCheckEnabled":"N","ruleName":"AutoDiscovery_BadDataCheck_FIRST_NAME","nullFilterColumn":"FIRST_NAME","businessAttributeId":"","columnName":"FIRST_NAME","activeFlag":false},{"ruleCategory":"Auto Discovery","ruleReference":50,"tagId":[],"rightTemplateFilterCondition":"","threshold":3,"ruleExpression":"^[0-9{3}$","dimensionName":"Accuracy","ruleDescription":"Invalid RegEx patterns < Threshold","rowId":1294540,"suggestionReason":"","idApp":31646,"ruleCode":"0","businessAttributes":"","defectCode":"","dimensionId":5,"ruleType":"Pattern Check","customOrGlobalRuleId":0,"agingCheckEnabled":"N","ruleName":"AutoDiscovery_PatternCheck_EMP_ID","nullFilterColumn":"EMP_ID","businessAttributeId":"","columnName":"EMP_ID","activeFlag":false},{"ruleCategory":"Auto Discovery","ruleReference":46,"tagId":[],"rightTemplateFilterCondition":"","threshold":3,"ruleExpression":"5","dimensionName":"Completeness","ruleDescription":"Elements w/Invalid Max length < Threshold","rowId":1294532,"suggestionReason":"","idApp":31646,"ruleCode":"0","businessAttributes":"","defectCode":"","dimensionId":3,"ruleType":"Max Length Check","customOrGlobalRuleId":0,"agingCheckEnabled":"N","ruleName":"AutoDiscovery_MaxLengthCheck_LAST_NAME","nullFilterColumn":"LAST_NAME","businessAttributeId":"","columnName":"LAST_NAME","activeFlag":false},{"ruleCategory":"Auto Discovery","ruleReference":47,"tagId":[],"rightTemplateFilterCondition":"","threshold":3,"ruleExpression":"","dimensionName":"Validity","ruleDescription":"Invalid data type < Threshold","rowId":1294536,"suggestionReason":"","idApp":31646,"ruleCode":"0","businessAttributes":"","defectCode":"","dimensionId":2,"ruleType":"Bad Data Check","customOrGlobalRuleId":0,"agingCheckEnabled":"N","ruleName":"AutoDiscovery_BadDataCheck_EMP_ID","nullFilterColumn":"EMP_ID","businessAttributeId":"","columnName":"EMP_ID","activeFlag":false},{"ruleCategory":"Auto Discovery","ruleReference":49,"tagId":[],"rightTemplateFilterCondition":"","threshold":3,"ruleExpression":"Mumbai","dimensionName":"Validity","ruleDescription":"Invalid default values < Threshold","rowId":1294538,"suggestionReason":"","idApp":31646,"ruleCode":"0","businessAttributes":"","defectCode":"","dimensionId":2,"ruleType":"Default Check","customOrGlobalRuleId":0,"agingCheckEnabled":"N","ruleName":"AutoDiscovery_DefaultCheck_CITY","nullFilterColumn":"CITY","businessAttributeId":"","columnName":"CITY","activeFlag":false},{"ruleCategory":"Auto Discovery","ruleReference":51,"tagId":[],"rightTemplateFilterCondition":"","threshold":3,"ruleExpression":"^[A-Za-z]{4}$","dimensionName":"Accuracy","ruleDescription":"Invalid RegEx patterns < Threshold","rowId":1294541,"suggestionReason":"","idApp":31646,"ruleCode":"0","businessAttributes":"","defectCode":"","dimensionId":5,"ruleType":"Pattern Check","customOrGlobalRuleId":0,"agingCheckEnabled":"N","ruleName":"AutoDiscovery_PatternCheck_LAST_NAME","nullFilterColumn":"LAST_NAME","businessAttributeId":"","columnName":"LAST_NAME","activeFlag":false},{"ruleCategory":"Auto Discovery","ruleReference":55,"tagId":[],"rightTemplateFilterCondition":"","threshold":0,"ruleExpression":"","dimensionName":"Uniqueness","ruleDescription":"Custom column dups < Threshold","rowId":1294550,"suggestionReason":"","idApp":31646,"ruleCode":"0","businessAttributes":"","defectCode":"","dimensionId":59,"ruleType":"Duplicate Check SelectedFields","customOrGlobalRuleId":0,"agingCheckEnabled":"N","ruleName":"AutoDiscovery_DuplicateCheckSelectedFields_FIRST_NAME","nullFilterColumn":"FIRST_NAME","businessAttributeId":"","columnName":"FIRST_NAME","activeFlag":false},{"ruleCategory":"Auto Discovery","ruleReference":52,"tagId":[],"rightTemplateFilterCondition":"","threshold":10,"dimensionName":"Accuracy","ruleDescription":"Invalid patterns < Threshold","rowId":1294546,"suggestionReason":"","idApp":31646,"ruleCode":"0","businessAttributes":"","defectCode":"","dimensionId":5,"ruleType":"Default Pattern Check","customOrGlobalRuleId":0,"agingCheckEnabled":"N","ruleName":"AutoDiscovery_DefaultPatternCheck_FIRST_NAME","nullFilterColumn":"FIRST_NAME","businessAttributeId":"","columnName":"FIRST_NAME","activeFlag":false},{"ruleCategory":"Auto Discovery","ruleReference":54,"tagId":[],"rightTemplateFilterCondition":"","threshold":0,"ruleExpression":"","dimensionName":"Uniqueness","ruleDescription":"Composite key dups < Threshold","rowId":1294548,"suggestionReason":"","idApp":31646,"ruleCode":"0","businessAttributes":"","defectCode":"","dimensionId":59,"ruleType":"Duplicate Check PrimaryFields","customOrGlobalRuleId":0,"agingCheckEnabled":"N","ruleName":"AutoDiscovery_DuplicateCheckPrimaryFields_CITY","nullFilterColumn":"CITY","businessAttributeId":"","columnName":"CITY","activeFlag":false},{"ruleCategory":"Auto Discovery","ruleReference":56,"tagId":[],"rightTemplateFilterCondition":"","threshold":3,"ruleExpression":"","dimensionName":"Consistency","ruleDescription":"Column values inconsistent with historical behavior < Threshold","rowId":1294552,"suggestionReason":"","idApp":31646,"ruleCode":"0","businessAttributes":"","defectCode":"","dimensionId":4,"ruleType":"Value Anomaly Check","customOrGlobalRuleId":0,"agingCheckEnabled":"N","ruleName":"AutoDiscovery_ValueAnomalyCheck_AGE_EMP","nullFilterColumn":"AGE_EMP","businessAttributeId":"","columnName":"AGE_EMP","activeFlag":false},{"ruleCategory":"Auto Discovery","ruleReference":1,"tagId":[],"rightTemplateFilterCondition":"","threshold":0,"ruleExpression":"","dimensionName":"Uniqueness","ruleDescription":"Composite key dups < Threshold","rowId":1294442,"suggestionReason":"","idApp":31646,"ruleCode":"","businessAttributes":"","defectCode":"","dimensionId":59,"ruleType":"Duplicate Check PrimaryFields","customOrGlobalRuleId":0,"agingCheckEnabled":"N","ruleName":"AutoDiscovery_DuplicateCheckPrimaryFields_EMP_ID","nullFilterColumn":"EMP_ID","businessAttributeId":"","columnName":"EMP_ID","is_critical":"N","activeFlag":false},{"ruleCategory":"Auto Discovery","ruleReference":2,"tagId":[],"rightTemplateFilterCondition":"","threshold":0,"ruleExpression":"","dimensionName":"Completeness","ruleDescription":"Null or blank < Threshold","rowId":1294443,"suggestionReason":"","idApp":31646,"ruleCode":"","businessAttributes":"","defectCode":"","dimensionId":3,"ruleType":"Null Check","customOrGlobalRuleId":0,"agingCheckEnabled":"N","ruleName":"AutoDiscovery_NullCheck_EMP_ID","nullFilterColumn":"EMP_ID","businessAttributeId":"","columnName":"EMP_ID","is_critical":"N","activeFlag":false},{"ruleCategory":"Auto Discovery","ruleReference":3,"tagId":[],"rightTemplateFilterCondition":"","threshold":9,"ruleExpression":"","dimensionName":"Completeness","ruleDescription":"Null or blank < Threshold","rowId":1294444,"suggestionReason":"","idApp":31646,"ruleCode":"","businessAttributes":"","defectCode":"","dimensionId":3,"ruleType":"Null Check","customOrGlobalRuleId":0,"agingCheckEnabled":"N","ruleName":"AutoDiscovery_NullCheck_FIRST_NAME","nullFilterColumn":"FIRST_NAME","businessAttributeId":"","columnName":"FIRST_NAME","is_critical":"N","activeFlag":false},{"ruleCategory":"Auto Discovery","ruleReference":4,"tagId":[],"rightTemplateFilterCondition":"","threshold":0,"ruleExpression":"","dimensionName":"Completeness","ruleDescription":"Null or blank < Threshold","rowId":1294445,"suggestionReason":"","idApp":31646,"ruleCode":"","businessAttributes":"","defectCode":"","dimensionId":3,"ruleType":"Null Check","customOrGlobalRuleId":0,"agingCheckEnabled":"N","ruleName":"AutoDiscovery_NullCheck_LAST_NAME","nullFilterColumn":"LAST_NAME","businessAttributeId":"","columnName":"LAST_NAME","is_critical":"N","activeFlag":false},{"ruleCategory":"Auto Discovery","ruleReference":5,"tagId":[],"rightTemplateFilterCondition":"","threshold":0,"ruleExpression":"","dimensionName":"Completeness","ruleDescription":"Null or blank < Threshold","rowId":1294446,"suggestionReason":"","idApp":31646,"ruleCode":"","businessAttributes":"","defectCode":"","dimensionId":3,"ruleType":"Null Check","customOrGlobalRuleId":0,"agingCheckEnabled":"N","ruleName":"AutoDiscovery_NullCheck_CITY","nullFilterColumn":"CITY","businessAttributeId":"","columnName":"CITY","is_critical":"N","activeFlag":false},{"ruleCategory":"Auto Discovery","ruleReference":6,"tagId":[],"rightTemplateFilterCondition":"","threshold":0,"ruleExpression":"","dimensionName":"Completeness","ruleDescription":"Null or blank < Threshold","rowId":1294447,"suggestionReason":"","idApp":31646,"ruleCode":"","businessAttributes":"","defectCode":"","dimensionId":3,"ruleType":"Null Check","customOrGlobalRuleId":0,"agingCheckEnabled":"N","ruleName":"AutoDiscovery_NullCheck_AGE_EMP","nullFilterColumn":"AGE_EMP","businessAttributeId":"","columnName":"AGE_EMP","is_critical":"N","activeFlag":false},{"ruleCategory":"Auto Discovery","ruleReference":7,"tagId":[],"rightTemplateFilterCondition":"","threshold":0,"ruleExpression":"","dimensionName":"Completeness","ruleDescription":"Null or blank < Threshold","rowId":1294448,"suggestionReason":"","idApp":31646,"ruleCode":"","businessAttributes":"","defectCode":"","dimensionId":3,"ruleType":"Null Check","customOrGlobalRuleId":0,"agingCheckEnabled":"N","ruleName":"AutoDiscovery_NullCheck_SALARY_EMP","nullFilterColumn":"SALARY_EMP","businessAttributeId":"","columnName":"SALARY_EMP","is_critical":"N","activeFlag":false},{"ruleCategory":"Auto Discovery","ruleReference":8,"tagId":[],"rightTemplateFilterCondition":"","threshold":0,"ruleExpression":"","dimensionName":"Completeness","ruleDescription":"Null or blank < Threshold","rowId":1294449,"suggestionReason":"","idApp":31646,"ruleCode":"","businessAttributes":"","defectCode":"","dimensionId":3,"ruleType":"Null Check","customOrGlobalRuleId":0,"agingCheckEnabled":"N","ruleName":"AutoDiscovery_NullCheck_EDUCATION","nullFilterColumn":"EDUCATION","businessAttributeId":"","columnName":"EDUCATION","is_critical":"N","activeFlag":false},{"ruleCategory":"Auto Discovery","ruleReference":9,"tagId":[],"rightTemplateFilterCondition":"","threshold":0,"ruleExpression":"","dimensionName":"Completeness","ruleDescription":"Null or blank < Threshold","rowId":1294450,"suggestionReason":"","idApp":31646,"ruleCode":"","businessAttributes":"","defectCode":"","dimensionId":3,"ruleType":"Null Check","customOrGlobalRuleId":0,"agingCheckEnabled":"N","ruleName":"AutoDiscovery_NullCheck_DATE_OF_BIRTH","nullFilterColumn":"DATE_OF_BIRTH","businessAttributeId":"","columnName":"DATE_OF_BIRTH","is_critical":"N","activeFlag":false},{"ruleCategory":"Auto Discovery","ruleReference":10,"tagId":[],"rightTemplateFilterCondition":"","threshold":0,"ruleExpression":"","dimensionName":"Completeness","ruleDescription":"Null or blank < Threshold","rowId":1294451,"suggestionReason":"","idApp":31646,"ruleCode":"","businessAttributes":"","defectCode":"","dimensionId":3,"ruleType":"Null Check","customOrGlobalRuleId":0,"agingCheckEnabled":"N","ruleName":"AutoDiscovery_NullCheck_DATE_OF_JOINING","nullFilterColumn":"DATE_OF_JOINING","businessAttributeId":"","columnName":"DATE_OF_JOINING","is_critical":"N","activeFlag":false},{"ruleCategory":"Auto Discovery","ruleReference":11,"tagId":[],"rightTemplateFilterCondition":"","threshold":10,"ruleExpression":"val:AAAAAper: (71%), val:AAAAAAper: (12%), val:AAAper: (9%)","dimensionName":"Accuracy","ruleDescription":"Invalid patterns < Threshold","rowId":1294452,"suggestionReason":"","idApp":31646,"ruleCode":"","businessAttributes":"","defectCode":"","dimensionId":5,"ruleType":"Default Pattern Check","customOrGlobalRuleId":0,"agingCheckEnabled":"N","ruleName":"AutoDiscovery_DefaultPatternCheck_LAST_NAME","nullFilterColumn":"LAST_NAME","businessAttributeId":"","columnName":"LAST_NAME","is_critical":"N","activeFlag":false},{"ruleCategory":"Auto Discovery","ruleReference":12,"tagId":[],"rightTemplateFilterCondition":"","threshold":10,"ruleExpression":"val:AAAAAAper: (100%)","dimensionName":"Accuracy","ruleDescription":"Invalid patterns < Threshold","rowId":1294453,"suggestionReason":"","idApp":31646,"ruleCode":"","businessAttributes":"","defectCode":"","dimensionId":5,"ruleType":"Default Pattern Check","customOrGlobalRuleId":0,"agingCheckEnabled":"N","ruleName":"AutoDiscovery_DefaultPatternCheck_EDUCATION","nullFilterColumn":"EDUCATION","businessAttributeId":"","columnName":"EDUCATION","is_critical":"N","activeFlag":false},{"ruleCategory":"Auto Discovery","ruleReference":13,"tagId":[],"rightTemplateFilterCondition":"","threshold":0,"ruleExpression":"","dimensionName":"Completeness","ruleDescription":"Elements w/Invalid length < Threshold","rowId":1294454,"suggestionReason":"","idApp":31646,"ruleCode":"","businessAttributes":"","defectCode":"","dimensionId":3,"ruleType":"Length Check","customOrGlobalRuleId":0,"agingCheckEnabled":"N","ruleName":"AutoDiscovery_LengthCheck_EDUCATION","nullFilterColumn":"EDUCATION","businessAttributeId":"","columnName":"EDUCATION","is_critical":"N","activeFlag":false},{"ruleCategory":"Auto Discovery","ruleReference":14,"tagId":[],"rightTemplateFilterCondition":"","threshold":0,"ruleExpression":"","dimensionName":"Validity","ruleDescription":"Out of range date values < Threshold","rowId":1294455,"suggestionReason":"","idApp":31646,"ruleCode":"","businessAttributes":"","defectCode":"","dimensionId":2,"ruleType":"Date Rule Check","customOrGlobalRuleId":0,"agingCheckEnabled":"N","ruleName":"AutoDiscovery_DateRuleCheck_DATE_OF_BIRTH","nullFilterColumn":"DATE_OF_BIRTH","businessAttributeId":"","columnName":"DATE_OF_BIRTH","is_critical":"N","activeFlag":false},{"ruleCategory":"Auto Discovery","ruleReference":15,"tagId":[],"rightTemplateFilterCondition":"","threshold":0,"ruleExpression":"","dimensionName":"Validity","ruleDescription":"Out of range date values < Threshold","rowId":1294456,"suggestionReason":"","idApp":31646,"ruleCode":"","businessAttributes":"","defectCode":"","dimensionId":2,"ruleType":"Date Rule Check","customOrGlobalRuleId":0,"agingCheckEnabled":"N","ruleName":"AutoDiscovery_DateRuleCheck_DATE_OF_JOINING","nullFilterColumn":"DATE_OF_JOINING","businessAttributeId":"","columnName":"DATE_OF_JOINING","is_critical":"N","activeFlag":false},{"ruleCategory":"Auto Discovery","ruleReference":16,"tagId":[],"rightTemplateFilterCondition":"","threshold":3,"ruleExpression":"","dimensionName":"Validity","ruleDescription":"Values outside predermined list","rowId":1294457,"suggestionReason":"","idApp":31646,"ruleCode":"","businessAttributes":"","defectCode":"","dimensionId":2,"ruleType":"Data Drift Check","customOrGlobalRuleId":0,"agingCheckEnabled":"N","ruleName":"AutoDiscovery_DataDriftCheck_EDUCATION","nullFilterColumn":"EDUCATION","businessAttributeId":"","columnName":"EDUCATION","is_critical":"N","activeFlag":false},{"ruleCategory":"Auto Discovery","ruleReference":43,"tagId":[],"rightTemplateFilterCondition":"","threshold":3,"ruleExpression":"","dimensionName":"Validity","ruleDescription":"Entire Dataset record count deviates from history < Threshold","rowId":1294484,"suggestionReason":"","idApp":31646,"ruleCode":"","businessAttributes":"","defectCode":"","dimensionId":2,"ruleType":"Record Count Anomaly","customOrGlobalRuleId":0,"agingCheckEnabled":"N","ruleName":"AutoDiscovery_RecordCountAnomaly","nullFilterColumn":"","businessAttributeId":"","columnName":"","is_critical":"N","activeFlag":false},{"ruleCategory":"Auto Discovery","ruleReference":53,"tagId":[],"rightTemplateFilterCondition":"","threshold":10,"dimensionName":"Accuracy","ruleDescription":"Invalid patterns < Threshold","rowId":1294547,"suggestionReason":"","idApp":31646,"ruleCode":"0","businessAttributes":"","defectCode":"","dimensionId":5,"ruleType":"Default Pattern Check","customOrGlobalRuleId":0,"agingCheckEnabled":"N","ruleName":"AutoDiscovery_DefaultPatternCheck_CITY","nullFilterColumn":"CITY","businessAttributeId":"","columnName":"CITY","activeFlag":false}]},"tags":[]}}