{"validation":{"listApplication":{"approveStatus":20,"badData":"N","pushDown":"N","keyBasedRecordCountAnomaly":"N","dupRowIdentityThreshold":0,"recordAnomalyCheck":"Y","historicEndDate":null,"incrementalTimestamp":null,"applyDerivedColumns":"N","offsetValue":null,"historicStartDate":null,"data_domain":2,"thresholdsApplyOption":0,"trimFunctionforMatch":"N","continuousFileMonitoring":"N","outOfNormCheck":"N","numericalStatThreshold":null,"entityColumn":"N","active":"yes","rollType":null,"endDateChk":null,"priority":null,"frequencyday":"unknown","fileNameValidation":"N","stringStatThreshold":null,"stagingApproveStatus":16,"updateFrequency":"Never","schema":null,"approveDate":null,"keyGroupRecordCountAnomaly":"N","timelinessKeyChk":"N","startDateChk":null,"coalesceFunctionforMatch":"N","appType":"Data Forensics","startTime":null,"maxLengthCheck":"N","stringStatCheck":"N","recordCountAnomalyThreshold":3,"correlationcheck":null,"lengthCheckThreshold":null,"workspaceId":null,"castFunctionforMatch":"N","dataDriftThreshold":null,"groupEquality":"N","sigmaCalcDays":0,"nonNullCheck":"Y","workspaceDomain":null,"idRightData":0,"frequencyDays":0,"automated":"N","dupRowAllThreshold":0,"endTime":null,"dataDriftCheck":"N","recordCountAnomaly":"Y","fileMonitoringType":null,"dataTrustMetricsCheck":"N","criticalRuleAvailable":null,"enablePhoneticMatching":null,"dGroupDateRuleCheck":"N","approveBy":0,"validityThreshold":1,"frequency":"unknown","approverName":"Admin User","createdAt":null,"duplicateCheck":null,"garbageRows":0,"idLeftData":0,"defaultPatternCheck":"Y","buildHistoricFingerPrint":"N","updatedAt":null,"updatedBy":null,"idData":27564,"colOrderValidation":"N","rollTargetSchemaId":0,"domainId":10,"slatime":null,"applyRules":"Y","domainName":"BANK","reprofiling":"N","name":"31754_test_mongo_Validation","isSegment":"N","projectName":"IT","projectId":18,"buildHistoricDayByDay":"N","tagIdList":null,"historicDateFormat":null,"subcribedEmailId":null,"patternCheck":"N","createdByUser":null,"groupEqualityThreshold":0,"description":"A default validation check","dGroupNullCheck":"N","accuracyRate":0,"recordAnomalyThreshold":null,"timeSeries":"None","dupRowIdentity":"Y","nonNullThreshold":null,"dupRowAll":"N","defaultValues":null,"windowTime":0,"csvDir":null,"prefix1":null,"dGroupDataDriftCheck":"N","numericalStatCheck":"Y","prefix2":null,"lengthCheck":"Y","matchingThreshold":0,"incrementalMatching":"N","defaultCheck":"N","validationJobSize":"medium","approveComments":null,"workspaceSubdomain":null,"idApp":31754,"createdBy":null,"dateRuleChk":"N"},"ruleCatalog":{"catalogRulesList":[{"ruleCategory":"Auto Discovery","ruleReference":2,"tagId":[],"rightTemplateFilterCondition":"","threshold":0,"ruleExpression":"","dimensionName":"Completeness","ruleDescription":"Null or blank < Threshold","rowId":1299066,"suggestionReason":"","idApp":31754,"ruleCode":"","businessAttributes":"","defectCode":"","dimensionId":3,"ruleType":"Null Check","customOrGlobalRuleId":0,"agingCheckEnabled":"N","nullFilterColumn":"AGE_EMP","ruleName":"AutoDiscovery_NullCheck_AGE_EMP","businessAttributeId":"","activeFlag":false,"columnName":"AGE_EMP","is_critical":"N"},{"ruleCategory":"Auto Discovery","ruleReference":5,"tagId":[],"rightTemplateFilterCondition":"","threshold":0,"ruleExpression":"","dimensionName":"Completeness","ruleDescription":"Null or blank < Threshold","rowId":1299069,"suggestionReason":"","idApp":31754,"ruleCode":"","businessAttributes":"","defectCode":"","dimensionId":3,"ruleType":"Null Check","customOrGlobalRuleId":0,"agingCheckEnabled":"N","nullFilterColumn":"DATE_OF_BIRTH","ruleName":"AutoDiscovery_NullCheck_DATE_OF_BIRTH","businessAttributeId":"","activeFlag":false,"columnName":"DATE_OF_BIRTH","is_critical":"N"},{"ruleCategory":"Auto Discovery","ruleReference":8,"tagId":[],"rightTemplateFilterCondition":"","threshold":0,"ruleExpression":"","dimensionName":"Completeness","ruleDescription":"Null or blank < Threshold","rowId":1299072,"suggestionReason":"","idApp":31754,"ruleCode":"","businessAttributes":"","defectCode":"","dimensionId":3,"ruleType":"Null Check","customOrGlobalRuleId":0,"agingCheckEnabled":"N","nullFilterColumn":"Employee_salary","ruleName":"AutoDiscovery_NullCheck_Employee_salary","businessAttributeId":"","activeFlag":false,"columnName":"Employee_salary","is_critical":"N"},{"ruleCategory":"Auto Discovery","ruleReference":9,"tagId":[],"rightTemplateFilterCondition":"","threshold":0,"ruleExpression":"","dimensionName":"Completeness","ruleDescription":"Null or blank < Threshold","rowId":1299073,"suggestionReason":"","idApp":31754,"ruleCode":"","businessAttributes":"","defectCode":"","dimensionId":3,"ruleType":"Null Check","customOrGlobalRuleId":0,"agingCheckEnabled":"N","nullFilterColumn":"SALARY_EMP","ruleName":"AutoDiscovery_NullCheck_SALARY_EMP","businessAttributeId":"","activeFlag":false,"columnName":"SALARY_EMP","is_critical":"N"},{"ruleCategory":"Auto Discovery","ruleReference":4,"tagId":[],"rightTemplateFilterCondition":"","threshold":0,"ruleExpression":"","dimensionName":"Completeness","ruleDescription":"Null or blank < Threshold","rowId":1299068,"suggestionReason":"","idApp":31754,"ruleCode":"","businessAttributes":"","defectCode":"","dimensionId":3,"ruleType":"Null Check","customOrGlobalRuleId":0,"agingCheckEnabled":"N","nullFilterColumn":"Customer_names","ruleName":"AutoDiscovery_NullCheck_Customer_names","businessAttributeId":"","activeFlag":false,"columnName":"Customer_names","is_critical":"Y"},{"ruleCategory":"Auto Discovery","ruleReference":6,"tagId":[],"rightTemplateFilterCondition":"","threshold":0,"ruleExpression":"","dimensionName":"Completeness","ruleDescription":"Null or blank < Threshold","rowId":1299070,"suggestionReason":"","idApp":31754,"ruleCode":"","businessAttributes":"","defectCode":"","dimensionId":3,"ruleType":"Null Check","customOrGlobalRuleId":0,"agingCheckEnabled":"N","nullFilterColumn":"Dealer_name","ruleName":"AutoDiscovery_NullCheck_Dealer_name","businessAttributeId":"","activeFlag":false,"columnName":"Dealer_name","is_critical":"Y"},{"ruleCategory":"Auto Discovery","ruleReference":7,"tagId":[],"rightTemplateFilterCondition":"","threshold":0,"ruleExpression":"","dimensionName":"Completeness","ruleDescription":"Null or blank < Threshold","rowId":1299071,"suggestionReason":"","idApp":31754,"ruleCode":"","businessAttributes":"","defectCode":"","dimensionId":3,"ruleType":"Null Check","customOrGlobalRuleId":0,"agingCheckEnabled":"N","nullFilterColumn":"Distributors_name","ruleName":"AutoDiscovery_NullCheck_Distributors_name","businessAttributeId":"","activeFlag":false,"columnName":"Distributors_name","is_critical":"Y"},{"ruleCategory":"Auto Discovery","ruleReference":12,"tagId":[],"rightTemplateFilterCondition":"","threshold":10,"ruleExpression":"val:##-##-####per: (82%), val:####-##-##A##:##:##.###Aper: (18%)","dimensionName":"Accuracy","ruleDescription":"Invalid patterns < Threshold","rowId":1299076,"suggestionReason":"","idApp":31754,"ruleCode":"","businessAttributes":"","defectCode":"","dimensionId":5,"ruleType":"Default Pattern Check","customOrGlobalRuleId":0,"agingCheckEnabled":"N","nullFilterColumn":"DATE_OF_BIRTH","ruleName":"AutoDiscovery_DefaultPatternCheck_DATE_OF_BIRTH","businessAttributeId":"","activeFlag":false,"columnName":"DATE_OF_BIRTH","is_critical":"N"},{"ruleCategory":"Auto Discovery","ruleReference":16,"tagId":[],"rightTemplateFilterCondition":"","threshold":0,"ruleExpression":"","dimensionName":"Completeness","ruleDescription":"Elements w/Invalid length < Threshold","rowId":1299080,"suggestionReason":"","idApp":31754,"ruleCode":"","businessAttributes":"","defectCode":"","dimensionId":3,"ruleType":"Length Check","customOrGlobalRuleId":0,"agingCheckEnabled":"N","nullFilterColumn":"DATE_OF_BIRTH","ruleName":"AutoDiscovery_LengthCheck_DATE_OF_BIRTH","businessAttributeId":"","activeFlag":false,"columnName":"DATE_OF_BIRTH","is_critical":"N"},{"ruleCategory":"Auto Discovery","ruleReference":17,"tagId":[],"rightTemplateFilterCondition":"","threshold":3,"ruleExpression":"","dimensionName":"Consistency","ruleDescription":"Entire microsegment behavior deviates from history < Threshold","rowId":1299081,"suggestionReason":"","idApp":31754,"ruleCode":"","businessAttributes":"","defectCode":"","dimensionId":4,"ruleType":"Numerical Statistics Check","customOrGlobalRuleId":0,"agingCheckEnabled":"N","nullFilterColumn":"SALARY_EMP","ruleName":"AutoDiscovery_NumericalStatisticsCheck_SALARY_EMP","businessAttributeId":"","activeFlag":false,"columnName":"SALARY_EMP","is_critical":"N"},{"ruleCategory":"Auto Discovery","ruleReference":18,"tagId":[],"rightTemplateFilterCondition":"","threshold":3,"ruleExpression":"","dimensionName":"Consistency","ruleDescription":"Column values inconsistent with historical behavior < Threshold","rowId":1299082,"suggestionReason":"","idApp":31754,"ruleCode":"","businessAttributes":"","defectCode":"","dimensionId":4,"ruleType":"Value Anomaly Check","customOrGlobalRuleId":0,"agingCheckEnabled":"N","nullFilterColumn":"SALARY_EMP","ruleName":"AutoDiscovery_ValueAnomalyCheck_SALARY_EMP","businessAttributeId":"","activeFlag":false,"columnName":"SALARY_EMP","is_critical":"N"},{"tagId":[],"threshold":0,"matchingRules":"","suggestionReason":"","defectCode":"","customOrGlobalRuleType":"referential","ruleType":"Global Rule","ruleName":"Ref","businessAttributeId":"","activeFlag":false,"is_critical":"N","ruleCategory":"Custom","ruleReference":19,"rightTemplateFilterCondition":"","ruleExpression":"DATE_OF_BIRTH<19","dimensionName":"Completeness","rowId":1299083,"idApp":31754,"ruleCode":"","businessAttributes":"","dimensionId":3,"filterCondition":"","customOrGlobalRuleId":6328,"agingCheckEnabled":"N","nullFilterColumn":"DATE_OF_BIRTH","columnName":"DATE_OF_BIRTH"},{"tagId":[],"threshold":0,"matchingRules":"","suggestionReason":"","defectCode":"","customOrGlobalRuleType":"sql internal rule","ruleType":"Global Rule","ruleName":"SqlInternalrule_FileSystem_HireDate","businessAttributeId":"","activeFlag":false,"is_critical":"N","ruleCategory":"Custom","ruleReference":20,"rightTemplateFilterCondition":"","ruleExpression":"Select * from INTERNALQUERY where DATE_OF_BIRTH>40","dimensionName":"Accuracy","rowId":1299084,"idApp":31754,"ruleCode":"","businessAttributes":"","dimensionId":5,"filterCondition":"","customOrGlobalRuleId":6330,"agingCheckEnabled":"N","nullFilterColumn":"DATE_OF_BIRTH","columnName":"DATE_OF_BIRTH"},{"tagId":[],"threshold":100,"matchingRules":"","suggestionReason":"","defectCode":"","customOrGlobalRuleType":"referential","ruleType":"Global Rule","ruleName":"Referential_Rule_Json","businessAttributeId":"","activeFlag":false,"is_critical":"N","ruleCategory":"Custom","ruleReference":21,"rightTemplateFilterCondition":"","ruleExpression":"DATE_OF_BIRTH>30","dimensionName":"Validity","rowId":1299085,"idApp":31754,"ruleCode":"","businessAttributes":"","dimensionId":2,"filterCondition":"","customOrGlobalRuleId":457,"agingCheckEnabled":"N","nullFilterColumn":"DATE_OF_BIRTH","columnName":"DATE_OF_BIRTH"},{"tagId":[],"threshold":0,"matchingRules":"","suggestionReason":"","defectCode":"","customOrGlobalRuleType":"referential","ruleType":"Global Rule","ruleName":"Ref","businessAttributeId":"","activeFlag":false,"is_critical":"N","ruleCategory":"Custom","ruleReference":22,"rightTemplateFilterCondition":"","ruleExpression":"DATE_OF_BIRTH<19","dimensionName":"Completeness","rowId":1299086,"idApp":31754,"ruleCode":"","businessAttributes":"","dimensionId":3,"filterCondition":"","customOrGlobalRuleId":402,"agingCheckEnabled":"N","nullFilterColumn":"DATE_OF_BIRTH","columnName":"DATE_OF_BIRTH"},{"tagId":[],"threshold":1,"matchingRules":"","suggestionReason":"","defectCode":"","customOrGlobalRuleType":"referential","ruleType":"Global Rule","ruleName":"test_123","businessAttributeId":"","activeFlag":false,"is_critical":"N","ruleCategory":"Custom","ruleReference":23,"rightTemplateFilterCondition":"","ruleExpression":"DATE_OF_BIRTH>12","dimensionName":"Numerical","rowId":1299087,"idApp":31754,"ruleCode":"","businessAttributes":"","dimensionId":15,"filterCondition":"","customOrGlobalRuleId":7813,"agingCheckEnabled":"N","nullFilterColumn":"DATE_OF_BIRTH","columnName":"DATE_OF_BIRTH"},{"ruleCategory":"Auto Discovery","ruleReference":13,"tagId":[],"rightTemplateFilterCondition":"","threshold":10,"ruleExpression":"val:AAAAAAAAAAA_A_##per: (81%), val:AAAAAAAAAAA_A_###per: (11%)","dimensionName":"Accuracy","ruleDescription":"Invalid patterns < Threshold","rowId":1299077,"suggestionReason":"","idApp":31754,"ruleCode":"","businessAttributes":"","defectCode":"","dimensionId":5,"ruleType":"Default Pattern Check","customOrGlobalRuleId":0,"agingCheckEnabled":"N","nullFilterColumn":"Dealer_name","ruleName":"AutoDiscovery_DefaultPatternCheck_Dealer_name","businessAttributeId":"","activeFlag":false,"columnName":"Dealer_name","is_critical":"Y"},{"tagId":[],"threshold":1,"matchingRules":"","suggestionReason":"","defectCode":"","customOrGlobalRuleType":"referential","ruleType":"Global Rule","ruleName":"global_reuseable_rule_ref","businessAttributeId":"","activeFlag":false,"is_critical":"N","ruleCategory":"Custom","ruleReference":24,"rightTemplateFilterCondition":"","ruleExpression":"DATE_OF_BIRTH>50","dimensionName":"Validity","rowId":1299088,"idApp":31754,"ruleCode":"","businessAttributes":"","dimensionId":2,"filterCondition":"","customOrGlobalRuleId":7353,"agingCheckEnabled":"N","nullFilterColumn":"DATE_OF_BIRTH","columnName":"DATE_OF_BIRTH"},{"tagId":[],"threshold":0,"matchingRules":"","suggestionReason":"","defectCode":"","customOrGlobalRuleType":"sql internal rule","ruleType":"Global Rule","ruleName":"SqlInternalrule_FileSystem_HireDate","businessAttributeId":"","activeFlag":false,"is_critical":"N","ruleCategory":"Custom","ruleReference":25,"rightTemplateFilterCondition":"","ruleExpression":"Select * from INTERNALQUERY where DATE_OF_BIRTH>40","dimensionName":"Accuracy","rowId":1299089,"idApp":31754,"ruleCode":"","businessAttributes":"","dimensionId":5,"filterCondition":"","customOrGlobalRuleId":1046,"agingCheckEnabled":"N","nullFilterColumn":"DATE_OF_BIRTH","columnName":"DATE_OF_BIRTH"},{"tagId":[],"threshold":100,"matchingRules":"","suggestionReason":"","defectCode":"","customOrGlobalRuleType":"referential","ruleType":"Global Rule","ruleName":"Referential_Rule_Json","businessAttributeId":"","activeFlag":false,"is_critical":"N","ruleCategory":"Custom","ruleReference":26,"rightTemplateFilterCondition":"","ruleExpression":"DATE_OF_BIRTH>30","dimensionName":"Validity","rowId":1299090,"idApp":31754,"ruleCode":"","businessAttributes":"","dimensionId":2,"filterCondition":"","customOrGlobalRuleId":6332,"agingCheckEnabled":"N","nullFilterColumn":"DATE_OF_BIRTH","columnName":"DATE_OF_BIRTH"},{"ruleCategory":"Auto Discovery","ruleReference":27,"tagId":[],"rightTemplateFilterCondition":"","threshold":3,"ruleExpression":"","dimensionName":"Validity","ruleDescription":"Entire Dataset record count deviates from history < Threshold","rowId":1299091,"suggestionReason":"","idApp":31754,"ruleCode":"","businessAttributes":"","defectCode":"","dimensionId":2,"ruleType":"Record Count Anomaly","customOrGlobalRuleId":0,"agingCheckEnabled":"N","nullFilterColumn":"","ruleName":"AutoDiscovery_RecordCountAnomaly","businessAttributeId":"","activeFlag":false,"columnName":"","is_critical":"N"},{"ruleCategory":"Auto Discovery","ruleReference":1,"tagId":[],"rightTemplateFilterCondition":"","threshold":0,"ruleExpression":"","dimensionName":"Uniqueness","ruleDescription":"Composite key dups < Threshold","rowId":1299065,"suggestionReason":"","idApp":31754,"ruleCode":"","businessAttributes":"","defectCode":"","dimensionId":59,"ruleType":"Duplicate Check PrimaryFields","customOrGlobalRuleId":0,"agingCheckEnabled":"N","nullFilterColumn":"test_id","ruleName":"AutoDiscovery_DuplicateCheckPrimaryFields_test_id","businessAttributeId":"","activeFlag":false,"columnName":"test_id","is_critical":"Y"},{"ruleCategory":"Auto Discovery","ruleReference":11,"tagId":[],"rightTemplateFilterCondition":"","threshold":0,"ruleExpression":"","dimensionName":"Completeness","ruleDescription":"Null or blank < Threshold","rowId":1299075,"suggestionReason":"","idApp":31754,"ruleCode":"","businessAttributes":"","defectCode":"","dimensionId":3,"ruleType":"Null Check","customOrGlobalRuleId":0,"agingCheckEnabled":"N","nullFilterColumn":"test_id","ruleName":"AutoDiscovery_NullCheck_test_id","businessAttributeId":"","activeFlag":false,"columnName":"test_id","is_critical":"Y"},{"ruleCategory":"Auto Discovery","ruleReference":15,"tagId":[],"rightTemplateFilterCondition":"","threshold":10,"ruleExpression":"val:#A#A##AAAA##AAAA######A#per: (48%), val:#A#A##AAAA##AAAA######AAper: (30%), val:#A#A##AAAA##AAAA#####A##per: (16%)","dimensionName":"Accuracy","ruleDescription":"Invalid patterns < Threshold","rowId":1299079,"suggestionReason":"","idApp":31754,"ruleCode":"","businessAttributes":"","defectCode":"","dimensionId":5,"ruleType":"Default Pattern Check","customOrGlobalRuleId":0,"agingCheckEnabled":"N","nullFilterColumn":"test_id","ruleName":"AutoDiscovery_DefaultPatternCheck_test_id","businessAttributeId":"","activeFlag":false,"columnName":"test_id","is_critical":"Y"},{"ruleCategory":"Auto Discovery","ruleReference":10,"tagId":[],"rightTemplateFilterCondition":"","threshold":0,"ruleExpression":"","dimensionName":"Completeness","ruleDescription":"Null or blank < Threshold","rowId":1299074,"suggestionReason":"","idApp":31754,"ruleCode":"","businessAttributes":"","defectCode":"","dimensionId":3,"ruleType":"Null Check","customOrGlobalRuleId":0,"agingCheckEnabled":"N","nullFilterColumn":"Workers_name","ruleName":"AutoDiscovery_NullCheck_Workers_name","businessAttributeId":"","activeFlag":false,"columnName":"Workers_name","is_critical":"Y"},{"ruleCategory":"Auto Discovery","ruleReference":14,"tagId":[],"rightTemplateFilterCondition":"","threshold":10,"ruleExpression":"val:AAAAAAAAAAA_A_##per: (81%), val:AAAAAAAAAAA_A_###per: (11%)","dimensionName":"Accuracy","ruleDescription":"Invalid patterns < Threshold","rowId":1299078,"suggestionReason":"","idApp":31754,"ruleCode":"","businessAttributes":"","defectCode":"","dimensionId":5,"ruleType":"Default Pattern Check","customOrGlobalRuleId":0,"agingCheckEnabled":"N","nullFilterColumn":"Distributors_name","ruleName":"AutoDiscovery_DefaultPatternCheck_Distributors_name","businessAttributeId":"","activeFlag":false,"columnName":"Distributors_name","is_critical":"Y"},{"ruleCategory":"Auto Discovery","ruleReference":3,"tagId":[],"rightTemplateFilterCondition":"","threshold":0,"ruleExpression":"","dimensionName":"Completeness","ruleDescription":"Null or blank < Threshold","rowId":1299067,"suggestionReason":"","idApp":31754,"ruleCode":"","businessAttributes":"","defectCode":"","dimensionId":3,"ruleType":"Null Check","customOrGlobalRuleId":0,"agingCheckEnabled":"N","nullFilterColumn":"Candidate_name","ruleName":"AutoDiscovery_NullCheck_Candidate_name","businessAttributeId":"","activeFlag":false,"columnName":"Candidate_name","is_critical":"Y"}]},"tags":[]}}